swarmauri_community/__init__.py
swarmauri_community/document_stores/__init__.py
swarmauri_community/document_stores/base/__init__.py
swarmauri_community/document_stores/concrete/RedisDocumentStore.py
swarmauri_community/document_stores/concrete/__init__.py
swarmauri_community/embeddings/__init__.py
swarmauri_community/embeddings/base/__init__.py
swarmauri_community/embeddings/concrete/Doc2VecEmbedding.py
swarmauri_community/embeddings/concrete/MlmEmbedding.py
swarmauri_community/embeddings/concrete/__init__.py
swarmauri_community/llms/__init__.py
swarmauri_community/llms/base/__init__.py
swarmauri_community/llms/concrete/LeptonAIImgGenModel.py
swarmauri_community/llms/concrete/LeptonAIModel.py
swarmauri_community/llms/concrete/PytesseractImg2TextModel.py
swarmauri_community/llms/concrete/__init__.py
swarmauri_community/measurements/__init__.py
swarmauri_community/measurements/base/__init__.py
swarmauri_community/measurements/concrete/MutualInformationMeasurement.py
swarmauri_community/measurements/concrete/TokenCountEstimatorMeasurement.py
swarmauri_community/measurements/concrete/__init__.py
swarmauri_community/parsers/__init__.py
swarmauri_community/parsers/base/__init__.py
swarmauri_community/parsers/concrete/BERTEmbeddingParser.py
swarmauri_community/parsers/concrete/EntityRecognitionParser.py
swarmauri_community/parsers/concrete/FitzPdfParser.py
swarmauri_community/parsers/concrete/PyPDF2Parser.py
swarmauri_community/parsers/concrete/PyPDFTKParser.py
swarmauri_community/parsers/concrete/TextBlobNounParser.py
swarmauri_community/parsers/concrete/TextBlobSentenceParser.py
swarmauri_community/parsers/concrete/__init__.py
swarmauri_community/retrievers/__init__.py
swarmauri_community/retrievers/base/__init__.py
swarmauri_community/retrievers/concrete/RedisDocumentRetriever.py
swarmauri_community/retrievers/concrete/__init__.py
swarmauri_community/state/__init__.py
swarmauri_community/state/concrete/ClipboardState.py
swarmauri_community/state/concrete/__init__.py
swarmauri_community-0.6.0.54.dist-info/METADATA
swarmauri_community-0.6.0.54.dist-info/WHEEL
swarmauri_community-0.6.0.54.dist-info/RECORD
